dflow/__init__.py
dflow/__main__.py
dflow/argo_objects.py
dflow/code_gen.py
dflow/common.py
dflow/config.py
dflow/context.py
dflow/context_syntax.py
dflow/dag.py
dflow/executor.py
dflow/io.py
dflow/main.py
dflow/op_template.py
dflow/py.typed
dflow/resource.py
dflow/slurm.py
dflow/step.py
dflow/steps.py
dflow/task.py
dflow/util_ops.py
dflow/utils.py
dflow/workflow.py
dflow/client/__init__.py
dflow/client/v1alpha1_artifact.py
dflow/client/v1alpha1_dag_task.py
dflow/client/v1alpha1_lifecycle_hook.py
dflow/client/v1alpha1_parameter.py
dflow/client/v1alpha1_retry_strategy.py
dflow/client/v1alpha1_sequence.py
dflow/client/v1alpha1_template.py
dflow/client/v1alpha1_value_from.py
dflow/client/v1alpha1_workflow_step.py
dflow/plugins/__init__.py
dflow/plugins/bohrium.py
dflow/plugins/datasets.py
dflow/plugins/dispatcher.py
dflow/plugins/launching.py
dflow/plugins/lebesgue.py
dflow/plugins/metadata.py
dflow/plugins/oss.py
dflow/plugins/ray.py
dflow/python/__init__.py
dflow/python/op.py
dflow/python/opio.py
dflow/python/python_op_template.py
dflow/python/utils.py
dflow/python/vendor/typeguard/__init__.py
dflow/python/vendor/typeguard/importhook.py
dflow/python/vendor/typeguard/py.typed
dflow/python/vendor/typeguard/pytest_plugin.py
pydflow-1.8.133.dist-info/licenses/LICENSE
pydflow-1.8.133.dist-info/METADATA
pydflow-1.8.133.dist-info/WHEEL
pydflow-1.8.133.dist-info/entry_points.txt
pydflow-1.8.133.dist-info/top_level.txt
pydflow-1.8.133.dist-info/RECORD
