Metadata-Version: 2.4
Name: pydflow
Version: 1.8.133
Summary: Dflow is a Python framework for constructing scientific computing workflows employing Argo Workflows as the workflow engine.
Home-page: https://github.com/deepmodeling/dflow
Author: Xinzijian Liu
Author-email: liuxzj@dp.tech
License: LGPLv3
Requires-Python: >=3.6
License-File: LICENSE
Requires-Dist: six
Requires-Dist: python-dateutil
Requires-Dist: urllib3
Requires-Dist: certifi
Requires-Dist: argo-workflows==5.0.0
Requires-Dist: jsonpickle
Requires-Dist: minio
Requires-Dist: kubernetes
Requires-Dist: pyyaml
Requires-Dist: cloudpickle==2.2.0
Requires-Dist: requests
Requires-Dist: tqdm
Requires-Dist: psutil
Requires-Dist: filelock
Dynamic: author
Dynamic: author-email
Dynamic: description
Dynamic: description-content-type
Dynamic: home-page
Dynamic: license
Dynamic: license-file
Dynamic: requires-dist
Dynamic: requires-python
Dynamic: summary
